gantty/__init__.py
gantty/__main__.py
gantty/gantty.py
gantty/time_tools.py
gantty-1.0.0.dist-info/LICENSE
gantty-1.0.0.dist-info/METADATA
gantty-1.0.0.dist-info/WHEEL
gantty-1.0.0.dist-info/entry_points.txt
gantty-1.0.0.dist-info/RECORD
