Metadata-Version: 2.1
Name: gantty
Version: 1.0.0
Summary: Gantt diagram generator
Home-page: https://github.com/RomoloPoliti-INAF/Gantty
License: GPL-3.0-or-later
Author: Romolo Politi
Author-email: romolo.politi@inaf.it
Requires-Python: >=3.10,<3.14
Classifier: License :: OSI Approved :: GNU General Public License v3 or later (GPLv3+)
Classifier: Programming Language :: Python :: 3
Classifier: Programming Language :: Python :: 3.10
Classifier: Programming Language :: Python :: 3.11
Classifier: Programming Language :: Python :: 3.12
Requires-Dist: matplotlib (>=3.10.0,<4.0.0)
Requires-Dist: pandas (>=2.2.3,<3.0.0)
Requires-Dist: rich-click (>=1.8.5,<2.0.0)
Project-URL: Repository, https://github.com/RomoloPoliti-INAF/Gantty
